{
    "bae612fd-e681-4899-a1ec-17ac0e15bea8": {
        "paletteKey": "NEUTRINOS_VIEW_SubNavbar",
        "commentid": null,
        "designerReference": [
            {
                "_key": "componentLabel",
                "_value": "SubNavbar",
                "_type": "kv",
                "_attrDef": "p",
                "_useAsLabel": true
            },
            {
                "_key": "style",
                "_value": "",
                "_type": "kv",
                "_attrDef": "p"
            },
            {
                "_key": "class",
                "_value": "",
                "_type": "dav",
                "_attrDef": "p"
            },
            {
                "_key": "subNavTitle",
                "_value": "Scanner",
                "_type": "kv",
                "_attrDef": "c"
            },
            {
                "_key": "[subNavTitle]",
                "_value": "",
                "_type": "kv",
                "_attrDef": "p",
                "_complexity": "advanced",
                "displayAs": "subNavTitle",
                "attrType": "INPUT",
                "inValid": false,
                "message": ""
            },
            {
                "_key": "IconUrl",
                "_value": "/Web/Icons/Cart.svg",
                "_type": "kv",
                "_attrDef": "c"
            },
            {
                "_key": "[IconUrl]",
                "_value": "",
                "_type": "kv",
                "_attrDef": "p",
                "_complexity": "advanced",
                "displayAs": "IconUrl",
                "attrType": "INPUT",
                "inValid": false,
                "message": ""
            },
            {
                "_key": "textColor",
                "_value": "white",
                "_type": "kv",
                "_attrDef": "c"
            },
            {
                "_key": "goto",
                "_value": "/ui/cart",
                "_type": "kv",
                "_attrDef": "c"
            },
            {
                "_key": "[textColor]",
                "_value": "",
                "_type": "kv",
                "_attrDef": "p",
                "_complexity": "advanced",
                "displayAs": "textColor",
                "attrType": "INPUT",
                "inValid": false,
                "message": ""
            },
            {
                "_key": "[goto]",
                "_value": "",
                "_type": "kv",
                "_attrDef": "p",
                "_complexity": "advanced",
                "displayAs": "goto",
                "attrType": "INPUT",
                "inValid": false,
                "message": ""
            },
            {
                "_key": "[backgroundColor]",
                "_value": "",
                "_type": "kv",
                "_attrDef": "p",
                "_complexity": "advanced",
                "displayAs": "backgroundColor",
                "attrType": "INPUT",
                "inValid": false,
                "message": ""
            },
            {
                "_key": "backgroundColor",
                "_value": "transparent",
                "_type": "kv",
                "_attrDef": "c"
            }
        ]
    },
    "7d275639-0612-366f-e243-20e95f5aa15d": {
        "paletteKey": "Html5",
        "isAdvancedComponent": true,
        "commentid": null,
        "designerReference": [
            {
                "_key": "style",
                "_value": "",
                "_type": "kv",
                "_attrDef": "p"
            },
            {
                "_key": "class",
                "_value": [
                    "div-ui-container"
                ],
                "_type": "dav",
                "_attrDef": "p"
            },
            {
                "_key": "htmlElement",
                "_value": "div",
                "_type": "dav",
                "_attrDef": "p",
                "_useAsLabel": true
            },
            {
                "_key": "tagType",
                "_value": "",
                "_type": "a",
                "_attrDef": "p",
                "_visibility": false
            },
            {
                "_key": "name",
                "_value": "",
                "_type": "kv",
                "_attrDef": "p",
                "_visibility": false
            },
            {
                "_key": "sandbox",
                "_value": "",
                "_type": "kv",
                "_attrDef": "p",
                "_visibility": false
            },
            {
                "_key": "src",
                "_value": "",
                "_type": "kv",
                "_attrDef": "p",
                "_visibility": false
            },
            {
                "_key": "srcdoc",
                "_value": "",
                "_type": "kv",
                "_attrDef": "p",
                "_visibility": false
            },
            {
                "_key": "width",
                "_value": "",
                "_type": "kv",
                "_attrDef": "p",
                "_visibility": false
            },
            {
                "_key": "[autoplay]",
                "_value": "",
                "_type": "kv",
                "_attrDef": "p",
                "_visibility": false
            },
            {
                "_key": "[loop]",
                "_value": "",
                "_type": "kv",
                "_attrDef": "p",
                "_visibility": false
            },
            {
                "_key": "data",
                "_value": "",
                "_type": "kv",
                "_attrDef": "p",
                "_visibility": false
            },
            {
                "_key": "audioSource",
                "_value": [],
                "_type": "a",
                "_attrDef": "p",
                "_visibility": false
            },
            {
                "_key": "videoSource",
                "_value": [],
                "_type": "a",
                "_attrDef": "p",
                "_visibility": false
            },
            {
                "_key": "audioDatasource",
                "_value": "",
                "_type": "a",
                "_attrDef": "p",
                "_visibility": false
            },
            {
                "_key": "audioSrc",
                "_value": "",
                "_type": "a",
                "_attrDef": "p",
                "_visibility": false
            },
            {
                "_key": "audioType",
                "_value": "",
                "_type": "a",
                "_attrDef": "p",
                "_visibility": false
            },
            {
                "_key": "videoDatasource",
                "_value": "",
                "_type": "a",
                "_attrDef": "p",
                "_visibility": false
            },
            {
                "_key": "videoSrc",
                "_value": "",
                "_type": "a",
                "_attrDef": "p",
                "_visibility": false
            },
            {
                "_key": "videoType",
                "_value": "",
                "_type": "a",
                "_attrDef": "p",
                "_visibility": false
            },
            {
                "_key": "(audioplay)",
                "_value": "",
                "_type": "a",
                "_attrDef": "p",
                "_visibility": false
            },
            {
                "_key": "(videoplay)",
                "_value": "",
                "_type": "a",
                "_attrDef": "p",
                "_visibility": false
            },
            {
                "_key": "(audiopause)",
                "_value": "",
                "_type": "kv",
                "_attrDef": "p",
                "_visibility": false
            },
            {
                "_key": "(videopause)",
                "_value": "",
                "_type": "kv",
                "_attrDef": "p",
                "_visibility": false
            },
            {
                "_key": "(audioended)",
                "_value": "",
                "_type": "kv",
                "_attrDef": "p",
                "_visibility": false
            },
            {
                "_key": "(videoended)",
                "_value": "",
                "_type": "kv",
                "_attrDef": "p",
                "_visibility": false
            }
        ],
        "a8ca3f8b-112a-3d9e-57c3-f24e5e00375c": {
            "paletteKey": "Html5",
            "parentEditorKey": "7d275639-0612-366f-e243-20e95f5aa15d",
            "isAdvancedComponent": true,
            "commentid": null,
            "designerReference": [
                {
                    "_key": "style",
                    "_value": "display:flex;align-items:center;justify-content:center;height:100%",
                    "_type": "kv",
                    "_attrDef": "p"
                },
                {
                    "_key": "class",
                    "_value": "",
                    "_type": "dav",
                    "_attrDef": "p"
                },
                {
                    "_key": "htmlElement",
                    "_value": "div",
                    "_type": "dav",
                    "_attrDef": "p",
                    "_useAsLabel": true
                },
                {
                    "_key": "tagType",
                    "_value": "",
                    "_type": "a",
                    "_attrDef": "p",
                    "_visibility": false
                },
                {
                    "_key": "name",
                    "_value": "",
                    "_type": "kv",
                    "_attrDef": "p",
                    "_visibility": false
                },
                {
                    "_key": "sandbox",
                    "_value": "",
                    "_type": "kv",
                    "_attrDef": "p",
                    "_visibility": false
                },
                {
                    "_key": "src",
                    "_value": "",
                    "_type": "kv",
                    "_attrDef": "p",
                    "_visibility": false
                },
                {
                    "_key": "srcdoc",
                    "_value": "",
                    "_type": "kv",
                    "_attrDef": "p",
                    "_visibility": false
                },
                {
                    "_key": "width",
                    "_value": "",
                    "_type": "kv",
                    "_attrDef": "p",
                    "_visibility": false
                },
                {
                    "_key": "[autoplay]",
                    "_value": "",
                    "_type": "kv",
                    "_attrDef": "p",
                    "_visibility": false
                },
                {
                    "_key": "[loop]",
                    "_value": "",
                    "_type": "kv",
                    "_attrDef": "p",
                    "_visibility": false
                },
                {
                    "_key": "data",
                    "_value": "",
                    "_type": "kv",
                    "_attrDef": "p",
                    "_visibility": false
                },
                {
                    "_key": "audioSource",
                    "_value": [],
                    "_type": "a",
                    "_attrDef": "p",
                    "_visibility": false
                },
                {
                    "_key": "videoSource",
                    "_value": [],
                    "_type": "a",
                    "_attrDef": "p",
                    "_visibility": false
                },
                {
                    "_key": "audioDatasource",
                    "_value": "",
                    "_type": "a",
                    "_attrDef": "p",
                    "_visibility": false
                },
                {
                    "_key": "audioSrc",
                    "_value": "",
                    "_type": "a",
                    "_attrDef": "p",
                    "_visibility": false
                },
                {
                    "_key": "audioType",
                    "_value": "",
                    "_type": "a",
                    "_attrDef": "p",
                    "_visibility": false
                },
                {
                    "_key": "videoDatasource",
                    "_value": "",
                    "_type": "a",
                    "_attrDef": "p",
                    "_visibility": false
                },
                {
                    "_key": "videoSrc",
                    "_value": "",
                    "_type": "a",
                    "_attrDef": "p",
                    "_visibility": false
                },
                {
                    "_key": "videoType",
                    "_value": "",
                    "_type": "a",
                    "_attrDef": "p",
                    "_visibility": false
                },
                {
                    "_key": "(audioplay)",
                    "_value": "",
                    "_type": "a",
                    "_attrDef": "p",
                    "_visibility": false
                },
                {
                    "_key": "(videoplay)",
                    "_value": "",
                    "_type": "a",
                    "_attrDef": "p",
                    "_visibility": false
                },
                {
                    "_key": "(audiopause)",
                    "_value": "",
                    "_type": "kv",
                    "_attrDef": "p",
                    "_visibility": false
                },
                {
                    "_key": "(videopause)",
                    "_value": "",
                    "_type": "kv",
                    "_attrDef": "p",
                    "_visibility": false
                },
                {
                    "_key": "(audioended)",
                    "_value": "",
                    "_type": "kv",
                    "_attrDef": "p",
                    "_visibility": false
                },
                {
                    "_key": "(videoended)",
                    "_value": "",
                    "_type": "kv",
                    "_attrDef": "p",
                    "_visibility": false
                }
            ],
            "d94d1b76-4995-ebaa-93d6-e41d18017f3e": {
                "paletteKey": "html-editor",
                "parentEditorKey": "a8ca3f8b-112a-3d9e-57c3-f24e5e00375c",
                "isAdvancedChildComponent": true,
                "commentid": null,
                "designerReference": [
                    {
                        "_key": "style",
                        "_value": "",
                        "_type": "kv",
                        "_attrDef": "p"
                    },
                    {
                        "_key": "class",
                        "_value": "",
                        "_type": "dav",
                        "_attrDef": "p"
                    },
                    {
                        "_key": "html",
                        "_value": "<svg id=\"dce-loading\" style=\"animation:turn 1.5s linear infinite;\" viewBox=\"0 0 1024 1024\" p-id=\"11986\" width=\"200\" height=\"200\">\r\n    <path d=\"M512.1 64.2c-35.4 0-64 28.7-64 64v128c0 35.4 28.7 64 64 64 35.4 0 64-28.7 64-64v-128c0-35.3-28.6-64-64-64zM320.4 328.3l-110.8-64c-30.6-17.7-69.8-7.2-87.4 23.4-17.7 30.6-7.2 69.8 23.4 87.4l110.8 64c30.6 17.7 69.8 7.2 87.4-23.4 17.7-30.6 7.2-69.8-23.4-87.4zM342.4 609.2c-17.7-30.6-56.8-41.1-87.4-23.4l-110.8 64c-30.6 17.7-41.1 56.8-23.4 87.4 17.7 30.6 56.8 41.1 87.4 23.4l110.8-64c30.6-17.7 41.1-56.8 23.4-87.4zM509.2 707.1c-35.4 0-64 28.7-64 64v128c0 35.4 28.7 64 64 64 35.4 0 64-28.7 64-64v-128c0-35.3-28.6-64-64-64zM875.8 652.2l-110.8-64c-30.6-17.7-69.8-7.2-87.4 23.4-17.7 30.6-7.2 69.8 23.4 87.4l110.8 64c30.6 17.7 69.8 7.2 87.4-23.4 17.7-30.6 7.2-69.7-23.4-87.4zM678.9 418.2c17.7 30.6 56.8 41.1 87.4 23.4l110.8-64c30.6-17.7 41.1-56.8 23.4-87.4-17.7-30.6-56.8-41.1-87.4-23.4l-110.8 64c-30.6 17.6-41.1 56.8-23.4 87.4z\" p-id=\"11987\"></path>\r\n</svg>",
                        "_type": "a",
                        "_attrDef": "p"
                    }
                ]
            }
        },
        "ba25d7f2-d028-f07f-d284-32ae9d3d9289": {
            "paletteKey": "Html5",
            "parentEditorKey": "7d275639-0612-366f-e243-20e95f5aa15d",
            "isAdvancedComponent": true,
            "commentid": null,
            "designerReference": [
                {
                    "_key": "style",
                    "_value": "",
                    "_type": "kv",
                    "_attrDef": "p"
                },
                {
                    "_key": "class",
                    "_value": [
                        "dce-video-container"
                    ],
                    "_type": "dav",
                    "_attrDef": "p"
                },
                {
                    "_key": "htmlElement",
                    "_value": "div",
                    "_type": "dav",
                    "_attrDef": "p",
                    "_useAsLabel": true
                },
                {
                    "_key": "tagType",
                    "_value": "",
                    "_type": "a",
                    "_attrDef": "p",
                    "_visibility": false
                },
                {
                    "_key": "name",
                    "_value": "",
                    "_type": "kv",
                    "_attrDef": "p",
                    "_visibility": false
                },
                {
                    "_key": "sandbox",
                    "_value": "",
                    "_type": "kv",
                    "_attrDef": "p",
                    "_visibility": false
                },
                {
                    "_key": "src",
                    "_value": "",
                    "_type": "kv",
                    "_attrDef": "p",
                    "_visibility": false
                },
                {
                    "_key": "srcdoc",
                    "_value": "",
                    "_type": "kv",
                    "_attrDef": "p",
                    "_visibility": false
                },
                {
                    "_key": "width",
                    "_value": "",
                    "_type": "kv",
                    "_attrDef": "p",
                    "_visibility": false
                },
                {
                    "_key": "[autoplay]",
                    "_value": "",
                    "_type": "kv",
                    "_attrDef": "p",
                    "_visibility": false
                },
                {
                    "_key": "[loop]",
                    "_value": "",
                    "_type": "kv",
                    "_attrDef": "p",
                    "_visibility": false
                },
                {
                    "_key": "data",
                    "_value": "",
                    "_type": "kv",
                    "_attrDef": "p",
                    "_visibility": false
                },
                {
                    "_key": "audioSource",
                    "_value": [],
                    "_type": "a",
                    "_attrDef": "p",
                    "_visibility": false
                },
                {
                    "_key": "videoSource",
                    "_value": [],
                    "_type": "a",
                    "_attrDef": "p",
                    "_visibility": false
                },
                {
                    "_key": "audioDatasource",
                    "_value": "",
                    "_type": "a",
                    "_attrDef": "p",
                    "_visibility": false
                },
                {
                    "_key": "audioSrc",
                    "_value": "",
                    "_type": "a",
                    "_attrDef": "p",
                    "_visibility": false
                },
                {
                    "_key": "audioType",
                    "_value": "",
                    "_type": "a",
                    "_attrDef": "p",
                    "_visibility": false
                },
                {
                    "_key": "videoDatasource",
                    "_value": "",
                    "_type": "a",
                    "_attrDef": "p",
                    "_visibility": false
                },
                {
                    "_key": "videoSrc",
                    "_value": "",
                    "_type": "a",
                    "_attrDef": "p",
                    "_visibility": false
                },
                {
                    "_key": "videoType",
                    "_value": "",
                    "_type": "a",
                    "_attrDef": "p",
                    "_visibility": false
                },
                {
                    "_key": "(audioplay)",
                    "_value": "",
                    "_type": "a",
                    "_attrDef": "p",
                    "_visibility": false
                },
                {
                    "_key": "(videoplay)",
                    "_value": "",
                    "_type": "a",
                    "_attrDef": "p",
                    "_visibility": false
                },
                {
                    "_key": "(audiopause)",
                    "_value": "",
                    "_type": "kv",
                    "_attrDef": "p",
                    "_visibility": false
                },
                {
                    "_key": "(videopause)",
                    "_value": "",
                    "_type": "kv",
                    "_attrDef": "p",
                    "_visibility": false
                },
                {
                    "_key": "(audioended)",
                    "_value": "",
                    "_type": "kv",
                    "_attrDef": "p",
                    "_visibility": false
                },
                {
                    "_key": "(videoended)",
                    "_value": "",
                    "_type": "kv",
                    "_attrDef": "p",
                    "_visibility": false
                }
            ]
        },
        "37e9829c-59ab-a820-5383-576bf2236938": {
            "paletteKey": "Html5",
            "parentEditorKey": "7d275639-0612-366f-e243-20e95f5aa15d",
            "isAdvancedComponent": true,
            "commentid": null,
            "designerReference": [
                {
                    "_key": "style",
                    "_value": "",
                    "_type": "kv",
                    "_attrDef": "p"
                },
                {
                    "_key": "class",
                    "_value": [
                        "dce-scanarea"
                    ],
                    "_type": "dav",
                    "_attrDef": "p"
                },
                {
                    "_key": "htmlElement",
                    "_value": "div",
                    "_type": "dav",
                    "_attrDef": "p",
                    "_useAsLabel": true
                },
                {
                    "_key": "tagType",
                    "_value": "",
                    "_type": "a",
                    "_attrDef": "p",
                    "_visibility": false
                },
                {
                    "_key": "name",
                    "_value": "",
                    "_type": "kv",
                    "_attrDef": "p",
                    "_visibility": false
                },
                {
                    "_key": "sandbox",
                    "_value": "",
                    "_type": "kv",
                    "_attrDef": "p",
                    "_visibility": false
                },
                {
                    "_key": "src",
                    "_value": "",
                    "_type": "kv",
                    "_attrDef": "p",
                    "_visibility": false
                },
                {
                    "_key": "srcdoc",
                    "_value": "",
                    "_type": "kv",
                    "_attrDef": "p",
                    "_visibility": false
                },
                {
                    "_key": "width",
                    "_value": "",
                    "_type": "kv",
                    "_attrDef": "p",
                    "_visibility": false
                },
                {
                    "_key": "[autoplay]",
                    "_value": "",
                    "_type": "kv",
                    "_attrDef": "p",
                    "_visibility": false
                },
                {
                    "_key": "[loop]",
                    "_value": "",
                    "_type": "kv",
                    "_attrDef": "p",
                    "_visibility": false
                },
                {
                    "_key": "data",
                    "_value": "",
                    "_type": "kv",
                    "_attrDef": "p",
                    "_visibility": false
                },
                {
                    "_key": "audioSource",
                    "_value": [],
                    "_type": "a",
                    "_attrDef": "p",
                    "_visibility": false
                },
                {
                    "_key": "videoSource",
                    "_value": [],
                    "_type": "a",
                    "_attrDef": "p",
                    "_visibility": false
                },
                {
                    "_key": "audioDatasource",
                    "_value": "",
                    "_type": "a",
                    "_attrDef": "p",
                    "_visibility": false
                },
                {
                    "_key": "audioSrc",
                    "_value": "",
                    "_type": "a",
                    "_attrDef": "p",
                    "_visibility": false
                },
                {
                    "_key": "audioType",
                    "_value": "",
                    "_type": "a",
                    "_attrDef": "p",
                    "_visibility": false
                },
                {
                    "_key": "videoDatasource",
                    "_value": "",
                    "_type": "a",
                    "_attrDef": "p",
                    "_visibility": false
                },
                {
                    "_key": "videoSrc",
                    "_value": "",
                    "_type": "a",
                    "_attrDef": "p",
                    "_visibility": false
                },
                {
                    "_key": "videoType",
                    "_value": "",
                    "_type": "a",
                    "_attrDef": "p",
                    "_visibility": false
                },
                {
                    "_key": "(audioplay)",
                    "_value": "",
                    "_type": "a",
                    "_attrDef": "p",
                    "_visibility": false
                },
                {
                    "_key": "(videoplay)",
                    "_value": "",
                    "_type": "a",
                    "_attrDef": "p",
                    "_visibility": false
                },
                {
                    "_key": "(audiopause)",
                    "_value": "",
                    "_type": "kv",
                    "_attrDef": "p",
                    "_visibility": false
                },
                {
                    "_key": "(videopause)",
                    "_value": "",
                    "_type": "kv",
                    "_attrDef": "p",
                    "_visibility": false
                },
                {
                    "_key": "(audioended)",
                    "_value": "",
                    "_type": "kv",
                    "_attrDef": "p",
                    "_visibility": false
                },
                {
                    "_key": "(videoended)",
                    "_value": "",
                    "_type": "kv",
                    "_attrDef": "p",
                    "_visibility": false
                }
            ],
            "f0640ffa-13e7-608f-0ec2-b7cd8b9e5709": {
                "paletteKey": "Html5",
                "parentEditorKey": "37e9829c-59ab-a820-5383-576bf2236938",
                "isAdvancedComponent": true,
                "isCommented": "true",
                "commentid": "1683099012406",
                "designerReference": [
                    {
                        "_key": "style",
                        "_value": "",
                        "_type": "kv",
                        "_attrDef": "p"
                    },
                    {
                        "_key": "class",
                        "_value": [
                            "dce-scanlight"
                        ],
                        "_type": "dav",
                        "_attrDef": "p"
                    },
                    {
                        "_key": "htmlElement",
                        "_value": "div",
                        "_type": "dav",
                        "_attrDef": "p",
                        "_useAsLabel": true
                    },
                    {
                        "_key": "tagType",
                        "_value": "",
                        "_type": "a",
                        "_attrDef": "p",
                        "_visibility": false
                    },
                    {
                        "_key": "name",
                        "_value": "",
                        "_type": "kv",
                        "_attrDef": "p",
                        "_visibility": false
                    },
                    {
                        "_key": "sandbox",
                        "_value": "",
                        "_type": "kv",
                        "_attrDef": "p",
                        "_visibility": false
                    },
                    {
                        "_key": "src",
                        "_value": "",
                        "_type": "kv",
                        "_attrDef": "p",
                        "_visibility": false
                    },
                    {
                        "_key": "srcdoc",
                        "_value": "",
                        "_type": "kv",
                        "_attrDef": "p",
                        "_visibility": false
                    },
                    {
                        "_key": "width",
                        "_value": "",
                        "_type": "kv",
                        "_attrDef": "p",
                        "_visibility": false
                    },
                    {
                        "_key": "[autoplay]",
                        "_value": "",
                        "_type": "kv",
                        "_attrDef": "p",
                        "_visibility": false
                    },
                    {
                        "_key": "[loop]",
                        "_value": "",
                        "_type": "kv",
                        "_attrDef": "p",
                        "_visibility": false
                    },
                    {
                        "_key": "data",
                        "_value": "",
                        "_type": "kv",
                        "_attrDef": "p",
                        "_visibility": false
                    },
                    {
                        "_key": "audioSource",
                        "_value": [],
                        "_type": "a",
                        "_attrDef": "p",
                        "_visibility": false
                    },
                    {
                        "_key": "videoSource",
                        "_value": [],
                        "_type": "a",
                        "_attrDef": "p",
                        "_visibility": false
                    },
                    {
                        "_key": "audioDatasource",
                        "_value": "",
                        "_type": "a",
                        "_attrDef": "p",
                        "_visibility": false
                    },
                    {
                        "_key": "audioSrc",
                        "_value": "",
                        "_type": "a",
                        "_attrDef": "p",
                        "_visibility": false
                    },
                    {
                        "_key": "audioType",
                        "_value": "",
                        "_type": "a",
                        "_attrDef": "p",
                        "_visibility": false
                    },
                    {
                        "_key": "videoDatasource",
                        "_value": "",
                        "_type": "a",
                        "_attrDef": "p",
                        "_visibility": false
                    },
                    {
                        "_key": "videoSrc",
                        "_value": "",
                        "_type": "a",
                        "_attrDef": "p",
                        "_visibility": false
                    },
                    {
                        "_key": "videoType",
                        "_value": "",
                        "_type": "a",
                        "_attrDef": "p",
                        "_visibility": false
                    },
                    {
                        "_key": "(audioplay)",
                        "_value": "",
                        "_type": "a",
                        "_attrDef": "p",
                        "_visibility": false
                    },
                    {
                        "_key": "(videoplay)",
                        "_value": "",
                        "_type": "a",
                        "_attrDef": "p",
                        "_visibility": false
                    },
                    {
                        "_key": "(audiopause)",
                        "_value": "",
                        "_type": "kv",
                        "_attrDef": "p",
                        "_visibility": false
                    },
                    {
                        "_key": "(videopause)",
                        "_value": "",
                        "_type": "kv",
                        "_attrDef": "p",
                        "_visibility": false
                    },
                    {
                        "_key": "(audioended)",
                        "_value": "",
                        "_type": "kv",
                        "_attrDef": "p",
                        "_visibility": false
                    },
                    {
                        "_key": "(videoended)",
                        "_value": "",
                        "_type": "kv",
                        "_attrDef": "p",
                        "_visibility": false
                    }
                ]
            }
        }
    },
    "32e56908-ffa3-514f-e90f-ec89a2892c84": {
        "paletteKey": "Html5",
        "isAdvancedComponent": true,
        "commentid": null,
        "designerReference": [
            {
                "_key": "style",
                "_value": "",
                "_type": "kv",
                "_attrDef": "p"
            },
            {
                "_key": "class",
                "_value": [
                    "products-list-container"
                ],
                "_type": "dav",
                "_attrDef": "p"
            },
            {
                "_key": "htmlElement",
                "_value": "div",
                "_type": "dav",
                "_attrDef": "p",
                "_useAsLabel": true
            },
            {
                "_key": "tagType",
                "_value": "",
                "_type": "a",
                "_attrDef": "p",
                "_visibility": false
            },
            {
                "_key": "name",
                "_value": "",
                "_type": "kv",
                "_attrDef": "p",
                "_visibility": false
            },
            {
                "_key": "sandbox",
                "_value": "",
                "_type": "kv",
                "_attrDef": "p",
                "_visibility": false
            },
            {
                "_key": "src",
                "_value": "",
                "_type": "kv",
                "_attrDef": "p",
                "_visibility": false
            },
            {
                "_key": "srcdoc",
                "_value": "",
                "_type": "kv",
                "_attrDef": "p",
                "_visibility": false
            },
            {
                "_key": "width",
                "_value": "",
                "_type": "kv",
                "_attrDef": "p",
                "_visibility": false
            },
            {
                "_key": "[autoplay]",
                "_value": "",
                "_type": "kv",
                "_attrDef": "p",
                "_visibility": false
            },
            {
                "_key": "[loop]",
                "_value": "",
                "_type": "kv",
                "_attrDef": "p",
                "_visibility": false
            },
            {
                "_key": "data",
                "_value": "",
                "_type": "kv",
                "_attrDef": "p",
                "_visibility": false
            },
            {
                "_key": "audioSource",
                "_value": [],
                "_type": "a",
                "_attrDef": "p",
                "_visibility": false
            },
            {
                "_key": "videoSource",
                "_value": [],
                "_type": "a",
                "_attrDef": "p",
                "_visibility": false
            },
            {
                "_key": "audioDatasource",
                "_value": "",
                "_type": "a",
                "_attrDef": "p",
                "_visibility": false
            },
            {
                "_key": "audioSrc",
                "_value": "",
                "_type": "a",
                "_attrDef": "p",
                "_visibility": false
            },
            {
                "_key": "audioType",
                "_value": "",
                "_type": "a",
                "_attrDef": "p",
                "_visibility": false
            },
            {
                "_key": "videoDatasource",
                "_value": "",
                "_type": "a",
                "_attrDef": "p",
                "_visibility": false
            },
            {
                "_key": "videoSrc",
                "_value": "",
                "_type": "a",
                "_attrDef": "p",
                "_visibility": false
            },
            {
                "_key": "videoType",
                "_value": "",
                "_type": "a",
                "_attrDef": "p",
                "_visibility": false
            },
            {
                "_key": "(audioplay)",
                "_value": "",
                "_type": "a",
                "_attrDef": "p",
                "_visibility": false
            },
            {
                "_key": "(videoplay)",
                "_value": "",
                "_type": "a",
                "_attrDef": "p",
                "_visibility": false
            },
            {
                "_key": "(audiopause)",
                "_value": "",
                "_type": "kv",
                "_attrDef": "p",
                "_visibility": false
            },
            {
                "_key": "(videopause)",
                "_value": "",
                "_type": "kv",
                "_attrDef": "p",
                "_visibility": false
            },
            {
                "_key": "(audioended)",
                "_value": "",
                "_type": "kv",
                "_attrDef": "p",
                "_visibility": false
            },
            {
                "_key": "(videoended)",
                "_value": "",
                "_type": "kv",
                "_attrDef": "p",
                "_visibility": false
            }
        ],
        "bca7c266-9f07-9d1a-8146-f4cd0d5190da": {
            "paletteKey": "NEUTRINOS_VIEW_Product",
            "parentEditorKey": "32e56908-ffa3-514f-e90f-ec89a2892c84",
            "commentid": null,
            "designerReference": [
                {
                    "_key": "componentLabel",
                    "_value": "Product",
                    "_type": "kv",
                    "_attrDef": "p",
                    "_useAsLabel": true
                },
                {
                    "_key": "style",
                    "_value": "",
                    "_type": "kv",
                    "_attrDef": "p"
                },
                {
                    "_key": "class",
                    "_value": "",
                    "_type": "dav",
                    "_attrDef": "p"
                },
                {
                    "_key": "[product]",
                    "_value": "product",
                    "_type": "kv",
                    "_attrDef": "c"
                },
                {
                    "_key": "*ngFor",
                    "_value": "let product of page.products",
                    "_type": "kv",
                    "_attrDef": "c"
                },
                {
                    "_key": "(deleteProductEvent)",
                    "_value": "",
                    "_type": "kv",
                    "_attrDef": "p",
                    "_complexity": "advanced",
                    "displayAs": "deleteProductEvent",
                    "attrType": "OUTPUT",
                    "inValid": true,
                    "message": "Property not available"
                },
                {
                    "_key": "(cancelProduct)",
                    "_value": "cancelProduct($event)",
                    "_type": "kv",
                    "_attrDef": "c",
                    "_customAttributeFlag": "flowpicker",
                    "objValue": {
                        "nodeID": "sd_4loRw6sSG8LPvbVc",
                        "functionName": "cancelProduct",
                        "activeTree": "pages",
                        "z": "sd_LIDAnDbHw9UbxkCR",
                        "input": [
                            "$event"
                        ]
                    }
                },
                {
                    "_key": "(changeCount)",
                    "_value": "changeCount($event)",
                    "_type": "kv",
                    "_attrDef": "c",
                    "_customAttributeFlag": "flowpicker",
                    "objValue": {
                        "nodeID": "sd_gNobqHCFhYTwWhFO",
                        "functionName": "changeCount",
                        "activeTree": "pages",
                        "z": "sd_LIDAnDbHw9UbxkCR",
                        "input": [
                            "$event"
                        ]
                    }
                }
            ]
        }
    }
}
